nf04/__init__.py
nf04_trace-0.3.dist-info/LICENSE
nf04_trace-0.3.dist-info/METADATA
nf04_trace-0.3.dist-info/WHEEL
nf04_trace-0.3.dist-info/top_level.txt
nf04_trace-0.3.dist-info/RECORD
